.gitignore
.travis.yml
CHANGES.rst
CONTRIBUTORS.rst
LICENSE.txt
README.rst
bootstrap.py
buildout.cfg
makecache.sh
setup.py
djc/__init__.py
djc.recipe2.egg-info/PKG-INFO
djc.recipe2.egg-info/SOURCES.txt
djc.recipe2.egg-info/dependency_links.txt
djc.recipe2.egg-info/entry_points.txt
djc.recipe2.egg-info/namespace_packages.txt
djc.recipe2.egg-info/not-zip-safe
djc.recipe2.egg-info/requires.txt
djc.recipe2.egg-info/top_level.txt
djc/recipe2/__init__.py
djc/recipe2/recipe.py
djc/recipe2/recipe.rst
djc/recipe2/tests.py